kickthespypet_api/__init__.py
kickthespypet_api/types.py
kickthespypet_api-0.0.5.dist-info/LICENSE
kickthespypet_api-0.0.5.dist-info/METADATA
kickthespypet_api-0.0.5.dist-info/WHEEL
kickthespypet_api-0.0.5.dist-info/RECORD
