Metadata-Version: 2.1
Name: kickthespypet-api
Version: 0.0.5
Summary: kickthespy.pet API wrapper
Home-page: https://github.com/timelessnesses/kickthespypet-api
License: MPL-2.0
Keywords: async,python3,kickthespy.pet,spy.pet
Author: timelesnesses
Author-email: timelessnesses@timelessnesses.me
Requires-Python: >=3.9,<4.0
Classifier: Development Status :: 4 - Beta
Classifier: License :: OSI Approved
Classifier: Programming Language :: Python :: 3
Classifier: Programming Language :: Python :: 3.9
Classifier: Programming Language :: Python :: 3.10
Classifier: Programming Language :: Python :: 3.11
Classifier: Programming Language :: Python :: 3.12
Requires-Dist: aiohttp (>=3.9.5,<4.0.0)
Requires-Dist: orjson (>=3.10.3,<4.0.0)
Requires-Dist: requests (>=2.31.0,<3.0.0)
Project-URL: Bug Tracker, https://github.com/timelessnesses/kickthespypet-api/issues
Project-URL: Repository, https://github.com/timelessnesses/kickthespypet-api
